odoo/addons/l10n_ro_account_bank_statement_import_mt940_ing/README.rst
odoo/addons/l10n_ro_account_bank_statement_import_mt940_ing/__init__.py
odoo/addons/l10n_ro_account_bank_statement_import_mt940_ing/__manifest__.py
odoo/addons/l10n_ro_account_bank_statement_import_mt940_ing/i18n/l10n_ro_account_bank_statement_import_mt940_ing.pot
odoo/addons/l10n_ro_account_bank_statement_import_mt940_ing/models/__init__.py
odoo/addons/l10n_ro_account_bank_statement_import_mt940_ing/models/account_bank_statement_import.py
odoo/addons/l10n_ro_account_bank_statement_import_mt940_ing/models/account_journal.py
odoo/addons/l10n_ro_account_bank_statement_import_mt940_ing/models/mt940.py
odoo/addons/l10n_ro_account_bank_statement_import_mt940_ing/readme/CONTRIBUTORS.rst
odoo/addons/l10n_ro_account_bank_statement_import_mt940_ing/readme/DESCRIPTION.rst
odoo/addons/l10n_ro_account_bank_statement_import_mt940_ing/static/description/icon.png
odoo/addons/l10n_ro_account_bank_statement_import_mt940_ing/static/description/icon.svg
odoo/addons/l10n_ro_account_bank_statement_import_mt940_ing/static/description/index.html
odoo/addons/l10n_ro_account_bank_statement_import_mt940_ing/test_files/test_ing_940.txt
odoo/addons/l10n_ro_account_bank_statement_import_mt940_ing/test_files/test_ing_940n.txt
odoo/addons/l10n_ro_account_bank_statement_import_mt940_ing/tests/__init__.py
odoo/addons/l10n_ro_account_bank_statement_import_mt940_ing/tests/test_import_bank_statement.py
odoo/addons/l10n_ro_account_bank_statement_import_mt940_ing/views/account_bank_statement_import_view.xml
odoo/addons/l10n_ro_account_bank_statement_import_mt940_ing/views/res_bank_view.xml
odoo14_addon_l10n_ro_account_bank_statement_import_mt940_ing-14.0.1.5.0.dist-info/METADATA
odoo14_addon_l10n_ro_account_bank_statement_import_mt940_ing-14.0.1.5.0.dist-info/WHEEL
odoo14_addon_l10n_ro_account_bank_statement_import_mt940_ing-14.0.1.5.0.dist-info/top_level.txt
odoo14_addon_l10n_ro_account_bank_statement_import_mt940_ing-14.0.1.5.0.dist-info/RECORD
